py-shasha/__init__.py
py-shasha/decision_tree.py
py-shasha/decision_tree_reg.py
py-shasha/knn.py
py-shasha/linear_regression.py
py-shasha/logistic_regression.py
py-shasha/multiple_regression.py
py-shasha/random_forest.py
py-shasha/svm.py
py-shasha/xgb_classifier.py
tests/__init__.py
tests/test_decision_tree.py
tests/test_knn.py
tests/test_linear_regression.py
tests/test_logistic_regression.py
tests/test_multiple_regression.py
tests/test_random_forest.py
tests/test_svm.py
tests/test_xgb_classifier.py
py_shasha-1.0.0.dist-info/LICENSE
py_shasha-1.0.0.dist-info/METADATA
py_shasha-1.0.0.dist-info/WHEEL
py_shasha-1.0.0.dist-info/top_level.txt
py_shasha-1.0.0.dist-info/RECORD
