Metadata-Version: 2.1
Name: py-shasha
Version: 1.0.0
Summary: A collection of machine learning models implemented from scratch
Home-page: https://github.com/shabari48/shasha
Author: Shabari Prakash
Author-email: shabariprakashsv@gmail.com
Classifier: Programming Language :: Python :: 3
Classifier: License :: OSI Approved :: MIT License
Classifier: Operating System :: OS Independent
Requires-Python: >=3.6
License-File: LICENSE
Requires-Dist: numpy
